databento/__init__.py
databento/common/__init__.py
databento/common/bentologging.py
databento/common/constants.py
databento/common/cram.py
databento/common/dbnstore.py
databento/common/enums.py
databento/common/error.py
databento/common/http.py
databento/common/iterator.py
databento/common/parsing.py
databento/common/publishers.py
databento/common/symbology.py
databento/common/system.py
databento/common/types.py
databento/common/validation.py
databento/historical/__init__.py
databento/historical/api/__init__.py
databento/historical/api/batch.py
databento/historical/api/metadata.py
databento/historical/api/symbology.py
databento/historical/api/timeseries.py
databento/historical/client.py
databento/live/__init__.py
databento/live/client.py
databento/live/gateway.py
databento/live/protocol.py
databento/live/session.py
databento/py.typed
databento/reference/__init__.py
databento/reference/api/__init__.py
databento/reference/api/adjustment.py
databento/reference/api/corporate.py
databento/reference/api/security.py
databento/reference/client.py
databento/version.py
databento-0.66.0.dist-info/METADATA
databento-0.66.0.dist-info/WHEEL
databento-0.66.0.dist-info/licenses/LICENSE
databento-0.66.0.dist-info/RECORD
