Metadata-Version: 2.4
Name: databento
Version: 0.66.0
Summary: Official Python client library for Databento
License-Expression: Apache-2.0
License-File: LICENSE
Author: Databento
Author-email: support@databento.com
Requires-Python: >=3.10
Classifier: Development Status :: 4 - Beta
Classifier: Operating System :: OS Independent
Classifier: Programming Language :: Python :: 3
Classifier: Programming Language :: Python :: 3.10
Classifier: Programming Language :: Python :: 3.11
Classifier: Programming Language :: Python :: 3.12
Classifier: Programming Language :: Python :: 3.13
Classifier: Topic :: Office/Business :: Financial
Classifier: Topic :: Office/Business :: Financial :: Investment
Classifier: Topic :: Software Development :: Libraries
Classifier: Topic :: Software Development :: Libraries :: Python Modules
Requires-Dist: aiohttp (>=3.8.3,<4.0.0) ; python_version < "3.12"
Requires-Dist: aiohttp (>=3.9.0,<4.0.0) ; python_version >= "3.12"
Requires-Dist: databento-dbn (>=0.44.0,<0.45.0)
Requires-Dist: numpy (>=1.23.5) ; python_version < "3.12"
Requires-Dist: numpy (>=1.26.0) ; python_version >= "3.12"
Requires-Dist: pandas (>=1.5.3)
Requires-Dist: pip-system-certs (>=4.0) ; platform_system == "Windows"
Requires-Dist: pyarrow (>=13.0.0)
Requires-Dist: requests (>=2.27.0)
Requires-Dist: zstandard (>=0.21.0)
Project-URL: Bug Tracker, https://github.com/databento/databento-python/issues
Project-URL: Documentation, https://databento.com/docs
Project-URL: Homepage, https://databento.com
Project-URL: Repository, https://github.com/databento/databento-python
